AUTHORS
LICENSE
MANIFEST.in
README.rst
setup.py
admin_import/__init__.py
admin_import/forms.py
admin_import/options.py
admin_import/locale/de/LC_MESSAGES/django.mo
admin_import/locale/de/LC_MESSAGES/django.po
admin_import/templates/admin/excel_import/changelist_view.html
admin_import/templates/admin/excel_import/import_xls.html
django_admin_import.egg-info/PKG-INFO
django_admin_import.egg-info/SOURCES.txt
django_admin_import.egg-info/dependency_links.txt
django_admin_import.egg-info/top_level.txt