Metadata-Version: 1.1
Name: django-admin-import
Version: 0.2.0
Summary: Import tool attachable to almost every Django admin
Home-page: http://github.com/allink/django-admin-import/
Author: Marc Egli
Author-email: egli@allink.ch
License: BSD License
Platform: OS Independent
Classifier: Development Status :: 3 - Alpha
Classifier: Environment :: Web Environment
Classifier: Framework :: Django
Classifier: Intended Audience :: Developers
Classifier: License :: OSI Approved :: BSD License
Classifier: Operating System :: OS Independent
Classifier: Programming Language :: Python
Classifier: Topic :: Internet :: WWW/HTTP :: Dynamic Content
Requires: Django(>=1.3)
